LICENSE.txt
MANIFEST.in
README.rst
distribute_setup.py
setup.py
bitpay/__init__.py
pybitpay.egg-info/PKG-INFO
pybitpay.egg-info/SOURCES.txt
pybitpay.egg-info/dependency_links.txt
pybitpay.egg-info/not-zip-safe
pybitpay.egg-info/requires.txt
pybitpay.egg-info/top_level.txt