Metadata-Version: 1.0
Name: pybitpay
Version: 0.1
Summary: Non-official Python API for BitPay Payment Gateway API.
Home-page: https://bitbucket.org/victorlin/pybitpay
Author: Victor Lin
Author-email: bornstub@gmail.com
License: MIT
Keywords: bitcoin api payment gateway bitpay
Platform: UNKNOWN
